tilesort-0.2.0.dist-info/METADATA
tilesort-0.2.0.dist-info/WHEEL
tilesort-0.2.0.dist-info/licenses/LICENSE
tilesort/__init__.py
tilesort/__init__.pyi
tilesort/_tilesort.cpython-311-darwin.so
tilesort/py.typed
tilesort-0.2.0.dist-info/RECORD
