Metadata-Version: 2.4
Name: tilesort
Version: 0.2.0
Classifier: Development Status :: 3 - Alpha
Classifier: Intended Audience :: Developers
Classifier: License :: OSI Approved :: MIT License
Classifier: License :: OSI Approved :: Apache Software License
Classifier: Programming Language :: Rust
Classifier: Programming Language :: Python :: Implementation :: CPython
Classifier: Programming Language :: Python :: Implementation :: PyPy
Classifier: Programming Language :: Python :: 3
Classifier: Programming Language :: Python :: 3.8
Classifier: Programming Language :: Python :: 3.9
Classifier: Programming Language :: Python :: 3.10
Classifier: Programming Language :: Python :: 3.11
Classifier: Programming Language :: Python :: 3.12
Classifier: Programming Language :: Python :: 3.13
Classifier: Programming Language :: Python :: 3.14
Classifier: Topic :: Software Development :: Libraries
Classifier: Topic :: Software Development :: Libraries :: Python Modules
Classifier: Typing :: Typed
License-File: LICENSE
Summary: A sorting algorithm optimized for datasets with pre-sorted contiguous blocks (tiles)
Keywords: sorting,algorithm,optimization,performance
Home-Page: https://github.com/evanjpw/tilesort
Author-email: Evan Williams <evanjpw@gmail.com>
License: MIT OR Apache-2.0
Requires-Python: >=3.8
Project-URL: Homepage, https://github.com/evanjpw/tilesort
Project-URL: Repository, https://github.com/evanjpw/tilesort
Project-URL: Documentation, https://github.com/evanjpw/tilesort#readme
Project-URL: Issues, https://github.com/evanjpw/tilesort/issues
